dvadmin_ak_sk/__init__.py
dvadmin_ak_sk/admin.py
dvadmin_ak_sk/apps.py
dvadmin_ak_sk/models.py
dvadmin_ak_sk/settings.py
dvadmin_ak_sk/urls.py
dvadmin_ak_sk/client/__init__.py
dvadmin_ak_sk/client/test.py
dvadmin_ak_sk/client/common/__init__.py
dvadmin_ak_sk/client/common/decorators.py
dvadmin_ak_sk/client/common/exception.py
dvadmin_ak_sk/client/common/utils.py
dvadmin_ak_sk/client/signature/__init__.py
dvadmin_ak_sk/client/signature/auth.py
dvadmin_ak_sk/fixtures/__init__.py
dvadmin_ak_sk/fixtures/initialize.py
dvadmin_ak_sk/libs/__init__.py
dvadmin_ak_sk/libs/authentication.py
dvadmin_ak_sk/libs/decorators.py
dvadmin_ak_sk/libs/exception.py
dvadmin_ak_sk/libs/utils.py
dvadmin_ak_sk/migrations/0001_initial.py
dvadmin_ak_sk/migrations/0002_initial.py
dvadmin_ak_sk/migrations/0003_akskmanage_is_deleted.py
dvadmin_ak_sk/migrations/__init__.py
dvadmin_ak_sk/views/__init__.py
dvadmin_ak_sk/views/ak_sk_manage.py
dvadmin_ak_sk-1.0.0.dist-info/METADATA
dvadmin_ak_sk-1.0.0.dist-info/WHEEL
dvadmin_ak_sk-1.0.0.dist-info/top_level.txt
dvadmin_ak_sk-1.0.0.dist-info/RECORD
