Metadata-Version: 2.1
Name: dvadmin-ak-sk
Version: 1.0.0
Summary: dvadmin-ak-sk 插件是dvadmin的一个ak/sk加密调用插件，使用Access Key Id / Secret Access Key加密的方法来验证某个请求的发送者身份。Access Key Id（AK）用于标示用户，Secret Access Key（SK）是用于加密认证字符串来验证认证字符串的密钥，其中SK必须保密。 AK/SK原理使用对称加解密。
Home-page: https://gitee.com/huge-dream/dvadmin-ak-sk
Author: 李强
Author-email: 1206709430@qq.com
Classifier: Programming Language :: Python :: 3
Classifier: License :: OSI Approved :: MIT License
Classifier: Operating System :: OS Independent
Requires-Python: >=3.6, <4
